{
  "left_sites":[
    {
      "url": "http://m.huffpost.com",
      "image": "m.huffpost.com.jpg"
    },
    {
      "url": "http://www.msnbc.com",
      "image": "www.msnbc.com.jpg"
    },
    {
      "url": "http:/www.nydailynews.com",
      "image": "www.nydailynews.com.jpg"
    },
    {
      "url":"http://talkingpointsmemo.com",
      "image":"talkingpointsmemo.com.jpg"
    },
    {
      "url":"http://www.slate.com",
      "image":"www.slate.com.jpg"
    },
    {
      "url":"https://news.vice.com",
      "image":"news.vice.com.jpg"
    },
    {
      "url":"http://www.motherjones.com",
      "image":"m.motherjones.com.jpg"
    }
  ],
  "right_sites": [
    {
      "url":"http://www.foxnews.com",
      "image":"www.foxnews.com.jpg"
    },
    {
      "url":"http://idrudgereport.com",
      "image":"idrudgereport.com.jpg"
    },
    {
      "url":"http://www.breitbart.com",
      "image":"www.breitbart.com.jpg"
    },
    {
      "url": "http://nypost.com",
      "image": "nypost.com.jpg"
    },
    {
      "url":"http://www.theblaze.com",
      "image":"www.theblaze.com.jpg"
    },
    {
      "url":"http://dailycaller.com",
      "image":"dailycaller.com.jpg"
    },
    {
      "url":"http://www.infowars.com",
      "image":"www.infowars.com.jpg"
    }
  ],
  "center_sites": [
    {
      "url":"http://www.nbcnews.com",
      "image":"www.nbcnews.com.jpg"
    },
    {
      "url":"http://www.cnn.com",
      "image":"www.cnn.com.jpg"
    },
    {
      "url":"https://www.washingtonpost.com",
      "image":"www.washingtonpost.com.jpg"
    },
    {
      "url":"http://www.nytimes.com",
      "image":"www.nytimes.com.jpg"
    }
    {
      "url": "https://www.apnews.com",
      "image": "www.apnews.com.jpg"
    },
    {
      "url": "http://mobile.reuters.com",
      "image": "mobile.reuters.com.jpg"
    },
    {
      "url": "http://www.npr.org",
      "image": "www.npr.org.jpg"
    }
  ]
}
